typed_schema_shot/__init__.py
typed_schema_shot/cfg.py
typed_schema_shot/compare_schemas.py
typed_schema_shot/core.py
typed_schema_shot/plugin.py
typed_schema_shot/schema_builder.py
typed_schema_shot/stats.py
typed_schema_shot/tracking.py
pytest_typed_schema_shot-0.1.9.dist-info/METADATA
pytest_typed_schema_shot-0.1.9.dist-info/WHEEL
pytest_typed_schema_shot-0.1.9.dist-info/entry_points.txt
pytest_typed_schema_shot-0.1.9.dist-info/licenses/LICENSE
pytest_typed_schema_shot-0.1.9.dist-info/RECORD
