Metadata-Version: 2.4
Name: pytest-typed-schema-shot
Version: 0.1.9
Summary: Pytest plugin for automatic JSON Schema generation and validation from examples
Project-URL: Homepage, https://github.com/Open-Inflation/pytest-typed-schema-shot
Author: Miskler
License: MIT
License-File: LICENSE
Keywords: click,genson,json,pytest,schema,validation
Classifier: Intended Audience :: Developers
Classifier: License :: OSI Approved :: MIT License
Classifier: Operating System :: Microsoft :: Windows
Classifier: Operating System :: POSIX :: Linux
Classifier: Programming Language :: Python :: 3
Classifier: Programming Language :: Python :: 3.10
Classifier: Programming Language :: Python :: 3.11
Classifier: Programming Language :: Python :: 3.12
Classifier: Programming Language :: Python :: 3.13
Classifier: Topic :: Software Development :: Libraries :: Python Modules
Classifier: Topic :: Utilities
Requires-Python: >=3.10
Requires-Dist: click
Requires-Dist: genson
Requires-Dist: jsonschema
Requires-Dist: pytest
